setup.cfg
setup.py
Cocopot.egg-info/PKG-INFO
Cocopot.egg-info/SOURCES.txt
Cocopot.egg-info/dependency_links.txt
Cocopot.egg-info/not-zip-safe
Cocopot.egg-info/top_level.txt
cocopot/__init__.py
cocopot/_compat.py
cocopot/app.py
cocopot/blueprints.py
cocopot/datastructures.py
cocopot/exceptions.py
cocopot/globals.py
cocopot/http.py
cocopot/local.py
cocopot/request.py
cocopot/response.py
cocopot/routing.py
cocopot/run.py
cocopot/testing.py
cocopot/utils.py